prft_json/__init__.py
prft_json/prft.py
prft_json-1.0.0.dist-info/LICENSE
prft_json-1.0.0.dist-info/METADATA
prft_json-1.0.0.dist-info/WHEEL
prft_json-1.0.0.dist-info/entry_points.txt
prft_json-1.0.0.dist-info/top_level.txt
prft_json-1.0.0.dist-info/RECORD
