Metadata-Version: 2.1
Name: prft-json
Version: 1.0.0
Summary: A tool to generate a json file tree structure of a project with .gitignore support
Author-email: Arkadii Artamonov <artamarkan@gmail.com>
Maintainer-email: Arkadii Artamonov <artamarkan@gmail.com>
License: MIT License
Keywords: file,tree,structure,file tree,file structure,json file tree
Classifier: Development Status :: 4 - Beta
Classifier: Programming Language :: Python :: 3
Classifier: License :: OSI Approved :: MIT License
Classifier: Operating System :: OS Independent
Requires-Python: >=3.8
License-File: LICENSE
